{
    "welcome": "مرحبًا!",
    "signup": "لا تفوت الفرصة، سجل الآن وابدأ رحلتك معنا!",
    "username": "اسم المستخدم",
    "email": "البريد الإلكتروني",
    "password": "كلمة المرور",
    "Confirm Password": "تأكيد كلمة المرور",
    "phone": "رقم الهاتف",
    "country": "الدولة",
    "city": "المدينة",
    "gender": "الجنس",
    "next": "التالي",
    "back": "السابق",
    "signupSuccess": "تم التسجيل بنجاح",
    "signupFailed": "فشل التسجيل",
    "validationError": "خطأ في التحقق",
    "haveAccount": "هل لديك حساب؟ تسجيل الدخول",
    "Next":"التالي",
    "fillAllFieldsCorrectly":"املأ جميع الحقول بشكل صحيح",
    "accountInfo":"معلومات الحساب",
    "additionalInfo":"معلومات إضافية",
    "enterUsername":"ادخل اسم المستخدم",
    "Username":"اسم المستخدم",
    "Email":"البريد الالكتروني",
    "enterEmail":"ادخل البريد الالكتروني",
    "enterPassword":"ادخل كلمه المرور",
    "Password":"كلمه المرور",
    "confirmPassword":"ادخل تاكيد كلمه المرور",
    "isRequired":"مطلوب",
    "passwordMinLength":"الحد الأدنى لطول كلمة المرور هو 8",
    "passwordsMustMatch":"يجب ان تكون تاكيد كلمه المرور مطابقه لكلمه المرور",
    "validEmail":"بريد إلكتروني غير صالح",
    "Phone":"رقم الهاتف",
    "enterPhone":"ادخل رقم الهاتف",
    "Country":"الدوله",
    "selectCountry":"اختر الدوله",
    "City":"المدينه",
    "enterCity":"ادخل المدينه",
    "Gender":"الجنس",
    "finish":"انشاء حساب",
    "phoneValid":"رقم هاتف غير صالح",
        "female":"انثي",
    "male":"ذكر",
    "otpVerification": "التحقق من OTP",
    "enterOtp": "يرجى إدخال OTP المرسل إلى صندوق بريدك.",
    "verifyOtp": "تحقق من OTP",
    "otp": "OTP",
    "verifyOtpButton": "تحقق من OTP",
    "sendOtpButton": "إرسال OTP",
    "otpSent": "تم إرسال OTP إلى عنوان بريدك الإلكتروني.",
    "verificationSuccessful": "التحقق ناجح",
    "verificationFailed": "فشل التحقق",
    "otpVerified": "تم التحقق من OTP {{otp}}!",
    "pleaseEnterOtp": "يرجى إدخال جميع 6 أرقام OTP.",
    "otpResent":"اعاده ارسال رمز otp",
    "otpResentMessage":"رسالة إعادة إرسال otp",
    "resendOtpIn": "يمكنك إعادة إرسال رمز التحقق بعد",
    "welcomeBack": "مرحباً بك مجددًا!",
    "loginPrompt": "يرجى تسجيل الدخول للوصول إلى لوحة التحكم الخاصة بك.",
    "login": "تسجيل الدخول",
    "forgotPassword": "هل نسيت كلمة المرور؟",
    "createAccount": "إنشاء حساب'",
    "loginSuccess": "تم تسجيل الدخول بنجاح",
    "loginError": "فشل في تسجيل الدخول",
    "storePage": "أنت الآن على صفحة المتجر!",
    "Please enter a valid email address":"يرجى إدخال عنوان بريد إلكتروني صالح",
    "Email is required":"البريد الإلكتروني مطلوب",
    "Password is required":" رقم المرور مطلوب"





  }
  